kieker/__init__.py
kieker/tools/__init__.py
kieker/tools/command_builder.py
kieker/tools/trace_analysis.py
kieker_for_jupyter-0.1.0.dist-info/licenses/LICENSE.txt
kieker_for_jupyter-0.1.0.dist-info/METADATA
kieker_for_jupyter-0.1.0.dist-info/WHEEL
kieker_for_jupyter-0.1.0.dist-info/top_level.txt
kieker_for_jupyter-0.1.0.dist-info/RECORD
