Metadata-Version: 2.4
Name: kieker_for_jupyter
Version: 0.1.0
Summary: Enhancing Kieker usability in Jupyter Notebooks
Author-email: Yorrick Josuttis <stu211751@mail.uni-kiel.de>
Project-URL: Homepage, https://github.com/kieker-monitoring/kieker
Project-URL: Issues, https://sustainkieker.kieker-monitoring.net/
Classifier: Programming Language :: Python :: 3
Classifier: Operating System :: OS Independent
Requires-Python: >=3.8
License-File: LICENSE.txt
Dynamic: license-file
